snemail/__init__.py
snemail/package.py
snemail-1.1.16.dist-info/LICENSE
snemail-1.1.16.dist-info/METADATA
snemail-1.1.16.dist-info/WHEEL
snemail-1.1.16.dist-info/top_level.txt
snemail-1.1.16.dist-info/RECORD
