Metadata-Version: 2.1
Name: snemail
Version: 1.1.16
Summary: 发送邮件库
Home-page: https://github.com/majormj/sendmail
Author: manji
Author-email: pnsm@qq.com
Classifier: Programming Language :: Python :: 3
Classifier: License :: OSI Approved :: MIT License
Classifier: Operating System :: OS Independent
Requires-Python: >=3
License-File: LICENSE
